SeaJsZhongwenWendang/README.md
SeaJsZhongwenWendang/__init__.py
SeaJsZhongwenWendang/__main__.py
SeaJsZhongwenWendang/file.epub
SeaJsZhongwenWendang/index.html
SeaJsZhongwenWendang/css/__init__.py
SeaJsZhongwenWendang/css/annotations.css
SeaJsZhongwenWendang/css/main.css
SeaJsZhongwenWendang/css/normalize.css
SeaJsZhongwenWendang/css/popup.css
SeaJsZhongwenWendang/font/__init__.py
SeaJsZhongwenWendang/font/fontello.eot
SeaJsZhongwenWendang/font/fontello.svg
SeaJsZhongwenWendang/font/fontello.ttf
SeaJsZhongwenWendang/font/fontello.woff
SeaJsZhongwenWendang/img/__init__.py
SeaJsZhongwenWendang/img/annotator-glyph-sprite.png
SeaJsZhongwenWendang/img/annotator-icon-sprite.png
SeaJsZhongwenWendang/img/apple-touch-icon.png
SeaJsZhongwenWendang/img/cancelfullscreen.png
SeaJsZhongwenWendang/img/close.png
SeaJsZhongwenWendang/img/fullscreen.png
SeaJsZhongwenWendang/img/loader.gif
SeaJsZhongwenWendang/img/menu-icon.png
SeaJsZhongwenWendang/img/save.png
SeaJsZhongwenWendang/img/saved.png
SeaJsZhongwenWendang/img/settings-s.png
SeaJsZhongwenWendang/img/settings.png
SeaJsZhongwenWendang/img/star.png
SeaJsZhongwenWendang/js/__init__.py
SeaJsZhongwenWendang/js/epub.js
SeaJsZhongwenWendang/js/epub.min.js
SeaJsZhongwenWendang/js/epub.min.map
SeaJsZhongwenWendang/js/hooks.min.js
SeaJsZhongwenWendang/js/hooks.min.map
SeaJsZhongwenWendang/js/reader.js
SeaJsZhongwenWendang/js/reader.js.map
SeaJsZhongwenWendang/js/reader.min.js
SeaJsZhongwenWendang/js/reader.min.map
SeaJsZhongwenWendang/js/hooks/__init__.py
SeaJsZhongwenWendang/js/hooks/extensions/__init__.py
SeaJsZhongwenWendang/js/hooks/extensions/highlight.js
SeaJsZhongwenWendang/js/libs/__init__.py
SeaJsZhongwenWendang/js/libs/jquery.min.js
SeaJsZhongwenWendang/js/libs/localforage.min.js
SeaJsZhongwenWendang/js/libs/screenfull.js
SeaJsZhongwenWendang/js/libs/screenfull.min.js
SeaJsZhongwenWendang/js/libs/zip.min.js
SeaJsZhongwenWendang/js/plugins/__init__.py
SeaJsZhongwenWendang/js/plugins/hypothesis.js
sea_js_zhongwen_wendang-2024.3.1.0.dist-info/METADATA
sea_js_zhongwen_wendang-2024.3.1.0.dist-info/WHEEL
sea_js_zhongwen_wendang-2024.3.1.0.dist-info/entry_points.txt
sea_js_zhongwen_wendang-2024.3.1.0.dist-info/top_level.txt
sea_js_zhongwen_wendang-2024.3.1.0.dist-info/RECORD
